moosir_common/__init__.py
moosir_common/live_traders/__init__.py
moosir_common/live_traders/core.py
moosir_common/model_engine/__init__.py
moosir_common/model_engine/models.py
moosir_common/model_engine/performance.py
moosir_common/model_engine/report_manager.py
moosir_common/risk_manager/__init__.py
moosir_common/risk_manager/common.py
moosir_common/risk_manager/risk_managers.py
moosir_common/risk_manager/utils.py
moosir_common-1.3.5.dist-info/METADATA
moosir_common-1.3.5.dist-info/WHEEL
moosir_common-1.3.5.dist-info/top_level.txt
moosir_common-1.3.5.dist-info/RECORD
