Metadata-Version: 2.1
Name: moosir-common
Version: 1.3.5
Summary: All common functionalities (live, research)
Home-page: UNKNOWN
Author: Ali A.
License: UNKNOWN
Platform: UNKNOWN
Requires-Python: ==3.7.*
Requires-Dist: numpy
Requires-Dist: pandas
Requires-Dist: backtrader
Requires-Dist: matplotlib
Requires-Dist: seaborn
Requires-Dist: scipy
Requires-Dist: scikit-learn
